serial/fountain_v1_serial.v
module fountain_v1_serial(
  input clk,
  input reset,
  input start,
  output reg done,
  input wire [63:0] data_in,
  output reg [63:0] data_out
);

  parameter N = 255; // block size
  parameter L = 10; // number of blocks to encode
  parameter K = 32; // number of non-zero coefficients

  // Linear Feedback Shift Register
  reg [63:0] lfsr;
  always @(posedge clk) begin
    if (reset) begin
      lfsr <= 8'hBC;
    end
    else begin
      lfsr <= {lfsr[62:0], lfsr[25] ^ lfsr[12] ^ lfsr[0]};
    end
  end

  // Generate matrix B
  reg [7:0] b [0:N-1][0:K-1];
  integer i, j;
  initial begin
    for (i = 0; i < N; i = i+1) begin
      for (j = 0; j < K; j = j+1) begin
        b[i][j] = lfsr;
        lfsr = {lfsr[6:0], lfsr[7] ^ lfsr[2]};
      end
    end
  end

  // Generate vector h
  reg [7:0] h [0:K-1];
  reg [7:0] data_in_reg; // new variable to store input data
  always @(posedge clk) begin
    if (start) begin
      for (i = 0; i < K; i = i+1) begin
        h[i] <= data_in_reg; // use data_in_reg instead of data_in
        data_in_reg <= data_in_reg + 1; // manipulate data_in_reg
      end
    end
  end

  // Generate vector z
  reg [7:0] z [0:N-1];
  reg [7:0] s [0:K-1];
  integer k, l, m, n;
  reg [7:0] output_reg [0:N*L-1]; // new variable to store output data
  reg [7:0] output_reg_i; // new variable to store current output byte
  integer output_index; // new variable to track output index
  always @(posedge clk) begin
    if (start) begin
      output_index = 0;
      for (k = 0; k < L; k = k+1) begin
        for (i = 0; i < N; i = i+1) begin
          z[i] = 0;
          for (j = 0; j < K; j = j+1) begin
            s[j] = h[j] ^ b[i][j];
          end
          for (l = 0; l < 8; l = l+1) begin
            for (m = 0; m < K; m = m+1) begin
              if (s[m][l] == 1) begin
                z[i][l] = z[i][l] ^ 1;
              end
            end
          end
          // Store output in output_reg
          for (n = 0; n < 8; n = n+1) begin
            output_reg[output_index][n] <= z[i][n];
          end
          output_index <= output_index + 1;
        end
      end
      done <= 1;
    end
  end
endmodule

serial/fountain_v1_tb.v
`timescale 1ns/1ns
`include "fountain_v1_serial.v"

module fountain_v1_tb();

    reg clk;
    reg rst;
    reg start;
    reg [63:0] data_in;
    wire [63:0] data_out;

    fountain_v1_serial uut (
        .clk(clk),
        .start(start),
        .data_in(data_in),
        .data_out(data_out)
    );

    initial begin
        $dumpfile("fountain_v1_tb.vcd");
        $dumpvars(0, fountain_v1_tb);

        // Initialize inputs
        clk = 0;
        rst = 0;
        start = 0;
        data_in = 8'b00000000;
        #10 rst = 1;
        #10 rst = 0;

        // Start the module
        #10 start = 1;
        #100 start = 0;

        // Send data
        #50 data_in = 8'b01010101;
        #50 data_in = 8'b10101010;

        // Wait for the module to finish
        #100000 $finish;
    end

    always #5 clk = ~clk;

endmodule

serial/fountain_v1_tb.vcd
$date
	Fri Apr 28 18:40:20 2023
$end
$version
	Icarus Verilog
$end
$timescale
	1ns
$end
$scope module fountain_v1_tb $end
$var wire 64 ! data_out [63:0] $end
$var reg 1 " clk $end
$var reg 64 # data_in [63:0] $end
$var reg 1 $ rst $end
$var reg 1 % start $end
$scope module uut $end
$var wire 1 " clk $end
$var wire 64 & data_in [63:0] $end
$var wire 1 ' reset $end
$var wire 1 % start $end
$var parameter 32 ( K $end
$var parameter 32 ) L $end
$var parameter 32 * N $end
$var reg 8 + data_in_reg [7:0] $end
$var reg 64 , data_out [63:0] $end
$var reg 1 - done $end
$var reg 64 . lfsr [63:0] $end
$var integer 32 / i [31:0] $end
$var integer 32 0 j [31:0] $end
$var integer 32 1 k [31:0] $end
$var integer 32 2 l [31:0] $end
$var integer 32 3 m [31:0] $end
$var integer 32 4 n [31:0] $end
$var integer 32 5 output_index [31:0] $end
$upscope $end
$upscope $end
$enddefinitions $end
$comment Show the parameter values. $end
$dumpall
b11111111 *
b1010 )
b100000 (
$end
#0
$dumpvars
bx 5
bx 4
bx 3
bx 2
bx 1
b100000 0
b11111111 /
b0xxxxxxxx .
x-
bx ,
bx +
z'
b0 &
0%
0$
b0 #
0"
bx !
$end
#5
b0xxxxxxxxx .
1"
#10
0"
1$
#15
b0xxxxxxxxxx .
1"
#20
0"
0$
#25
b0xxxxxxxxxxx .
1"
#30
0"
1%
#35
1-
b0xxxxxxxxxxxx .
b1000 4
b100000 3
b1000 2
b100000 0
b1010 1
b1 5
b11111111 /
1"
#40
0"
#45
b0xxxxxxxxxxxxx .
b1000 4
b100000 3
b1000 2
b100000 0
b100000 /
b1010 1
b1 5
1"
#50
0"
#55
b0xxxxxxxxxxxxxx .
b1000 4
b100000 3
b1000 2
b100000 0
b1010 1
b1 5
b11111111 /
1"
#60
0"
#65
b0xxxxxxxxxxxxxxx .
b1000 4
b100000 3
b1000 2
b100000 0
b100000 /
b1010 1
b1 5
1"
#70
0"
#75
b0xxxxxxxxxxxxxxxx .
b1000 4
b100000 3
b1000 2
b100000 0
b1010 1
b1 5
b11111111 /
1"
#80
0"
#85
b0xxxxxxxxxxxxxxxxx .
b1000 4
b100000 3
b1000 2
b100000 0
b100000 /
b1010 1
b1 5
1"
#90
0"
#95
b0xxxxxxxxxxxxxxxxxx .
b1000 4
b100000 3
b1000 2
b100000 0
b1010 1
b1 5
b11111111 /
1"
#100
0"
#105
b0xxxxxxxxxxxxxxxxxxx .
b1000 4
b100000 3
b1000 2
b100000 0
b100000 /
b1010 1
b1 5
1"
#110
0"
#115
b0xxxxxxxxxxxxxxxxxxxx .
b1000 4
b100000 3
b1000 2
b100000 0
b1010 1
b1 5
b11111111 /
1"
#120
0"
#125
b0xxxxxxxxxxxxxxxxxxxxx .
b1000 4
b100000 3
b1000 2
b100000 0
b100000 /
b1010 1
b1 5
1"
#130
0"
0%
#135
b0xxxxxxxxxxxxxxxxxxxxxx .
1"
#140
0"
#145
b0xxxxxxxxxxxxxxxxxxxxxxx .
1"
#150
0"
#155
b0xxxxxxxxxxxxxxxxxxxxxxxx .
1"
#160
0"
#165
b0xxxxxxxxxxxxxxxxxxxxxxxxx .
1"
#170
0"
#175
b0xxxxxxxxxxxxxxxxxxxxxxxxxx .
1"
#180
0"
b1010101 #
b1010101 &
#185
b0xxxxxxxxxxxxxxxxxxxxxxxxxxx .
1"
#190
0"
#195
b0xxxxxxxxxxxxxxxxxxxxxxxxxxxx .
1"
#200
0"
#205
b0xxxxxxxxxxxxxxxxxxxxxxxxxxxxx .
1"
#210
0"
#215
b0xxxxxxxxxxxxxxxxxxxxxxxxxxxxxx .
1"
#220
0"
#225
b0xxxxxxxxxxxxxxxxxxxxxxxxxxxxxxx .
1"
#230
0"
b10101010 #
b10101010 &
#235
b0xxxxxxxxxxxxxxxxxxxxxxxxxxxxxxxx .
1"
#240
0"
#245
b0xxxxxxxxxxxxxxxxxxxxxxxxxxxxxxxxx .
1"
#250
0"
#255
b0xxxxxxxxxxxxxxxxxxxxxxxxxxxxxxxxxx .
1"
#260
0"
#265
b0xxxxxxxxxxxxxxxxxxxxxxxxxxxxxxxxxxx .
1"
#270
0"
#275
b0xxxxxxxxxxxxxxxxxxxxxxxxxxxxxxxxxxxx .
1"
#280
0"
#285
b0xxxxxxxxxxxxxxxxxxxxxxxxxxxxxxxxxxxxx .
1"
#290
0"
#295
b0xxxxxxxxxxxxxxxxxxxxxxxxxxxxxxxxxxxxxx .
1"
#300
0"
#305
b0xxxxxxxxxxxxxxxxxxxxxxxxxxxxxxxxxxxxxxx .
1"
#310
0"
#315
b0xxxxxxxxxxxxxxxxxxxxxxxxxxxxxxxxxxxxxxxx .
1"
#320
0"
#325
b0xxxxxxxxxxxxxxxxxxxxxxxxxxxxxxxxxxxxxxxxx .
1"
#330
0"
#335
b0xxxxxxxxxxxxxxxxxxxxxxxxxxxxxxxxxxxxxxxxxx .
1"
#340
0"
#345
b0xxxxxxxxxxxxxxxxxxxxxxxxxxxxxxxxxxxxxxxxxxx .
1"
#350
0"
#355
b0xxxxxxxxxxxxxxxxxxxxxxxxxxxxxxxxxxxxxxxxxxxx .
1"
#360
0"
#365
b0xxxxxxxxxxxxxxxxxxxxxxxxxxxxxxxxxxxxxxxxxxxxx .
1"
#370
0"
#375
b0xxxxxxxxxxxxxxxxxxxxxxxxxxxxxxxxxxxxxxxxxxxxxx .
1"
#380
0"
#385
b0xxxxxxxxxxxxxxxxxxxxxxxxxxxxxxxxxxxxxxxxxxxxxxx .
1"
#390
0"
#395
b0xxxxxxxxxxxxxxxxxxxxxxxxxxxxxxxxxxxxxxxxxxxxxxxx .
1"
#400
0"
#405
b0xxxxxxxxxxxxxxxxxxxxxxxxxxxxxxxxxxxxxxxxxxxxxxxxx .
1"
#410
0"
#415
b0xxxxxxxxxxxxxxxxxxxxxxxxxxxxxxxxxxxxxxxxxxxxxxxxxx .
1"
#420
0"
#425
b0xxxxxxxxxxxxxxxxxxxxxxxxxxxxxxxxxxxxxxxxxxxxxxxxxxx .
1"
#430
0"
#435
b0xxxxxxxxxxxxxxxxxxxxxxxxxxxxxxxxxxxxxxxxxxxxxxxxxxxx .
1"
#440
0"
#445
b0xxxxxxxxxxxxxxxxxxxxxxxxxxxxxxxxxxxxxxxxxxxxxxxxxxxxx .
1"
#450
0"
#455
b0xxxxxxxxxxxxxxxxxxxxxxxxxxxxxxxxxxxxxxxxxxxxxxxxxxxxxx .
1"
#460
0"
#465
b0xxxxxxxxxxxxxxxxxxxxxxxxxxxxxxxxxxxxxxxxxxxxxxxxxxxxxxx .
1"
#470
0"
#475
b0xxxxxxxxxxxxxxxxxxxxxxxxxxxxxxxxxxxxxxxxxxxxxxxxxxxxxxxx .
1"
#480
0"
#485
b0xxxxxxxxxxxxxxxxxxxxxxxxxxxxxxxxxxxxxxxxxxxxxxxxxxxxxxxxx .
1"
#490
0"
#495
b0xxxxxxxxxxxxxxxxxxxxxxxxxxxxxxxxxxxxxxxxxxxxxxxxxxxxxxxxxx .
1"
#500
0"
#505
b0xxxxxxxxxxxxxxxxxxxxxxxxxxxxxxxxxxxxxxxxxxxxxxxxxxxxxxxxxxx .
1"
#510
0"
#515
b0xxxxxxxxxxxxxxxxxxxxxxxxxxxxxxxxxxxxxxxxxxxxxxxxxxxxxxxxxxxx .
1"
#520
0"
#525
b0xxxxxxxxxxxxxxxxxxxxxxxxxxxxxxxxxxxxxxxxxxxxxxxxxxxxxxxxxxxxx .
1"
#530
0"
#535
b0xxxxxxxxxxxxxxxxxxxxxxxxxxxxxxxxxxxxxxxxxxxxxxxxxxxxxxxxxxxxxx .
1"
#540
0"
#545
b0xxxxxxxxxxxxxxxxxxxxxxxxxxxxxxxxxxxxxxxxxxxxxxxxxxxxxxxxxxxxxxx .
1"
#550
0"
#555
bx .
1"
