parallel/fountain_v1_parallel.v
module fountain_v1_parallel(
  input clk,
  input reset,
  input start,
  output reg done,
  input wire [63:0] data_in,
  output reg [63:0] data_out
);

  parameter N = 255; // block size
  parameter L = 10; // number of blocks to encode
  parameter K = 32; // number of non-zero coefficients

  // Linear Feedback Shift Register
  reg [63:0] lfsr;
  always @(posedge clk) begin
    if (reset) begin
      lfsr <= 8'hBC;
    end
    else begin
      lfsr <= {lfsr[62:0], lfsr[25] ^ lfsr[12] ^ lfsr[0]};
    end
  end

  // Generate matrix B
  reg [7:0] b [0:N-1][0:K-1];
  integer i, j;
  initial begin
    for (i = 0; i < N; i = i+1) begin
      for (j = 0; j < K; j = j+1) begin
        b[i][j] = lfsr;
        lfsr = {lfsr[6:0], lfsr[7] ^ lfsr[2]};
      end
    end
  end

  // Generate vector h
  reg [7:0] h [0:K-1];
  reg [7:0] data_in_reg; // new variable to store input data
  always @(posedge clk) begin
    if (start) begin
      for (i = 0; i < K; i = i+1) begin
        h[i] <= data_in_reg; // use data_in_reg instead of data_in
        data_in_reg <= data_in_reg + 1; // manipulate data_in_reg
      end
    end
  end

  // Generate vector z
  reg [7:0] z [0:N-1][0:8];
  reg [7:0] s [0:K-1][0:8];
  integer k, i1, j1, l, m;
  always @(posedge clk) begin
  if (start) begin
    for (k = 0; k < L; k = k+1) begin
      for (i1 = 0; i1 < N; i1 = i1+1) begin
        for (j1 = 0; j1 < K; j1 = j1+1) begin
          s[j1][i1] = h[j1] ^ b[i1][j1];
        end
          for (l = 0; l < 8; l = l+1) begin
            z[i][l] = 8'h00; // initialize z to 0
              for (m = 0; m < K; m = m+1) begin
                if (s[m][l] == 1) begin
                  z[i1][l] = z[i1][l] ^ 1;
                end
            end
            data_out <= z[i1][l];
            done <= 0;
            #1 done <= 1;
          end
        end
      end
    end
  end

endmodule

parallel/fountain_v1_tb.v
`timescale 1ns/1ns
`include "fountain_v1_parallel.v"

module fountain_v1_tb();

    reg clk;
    reg rst;
    reg start;
    reg [63:0] data_in;
    wire [63:0] data_out;

    fountain_v1_parallel uut (
        .clk(clk),
        .start(start),
        .data_in(data_in),
        .data_out(data_out)
    );

    initial begin
        $dumpfile("fountain_v1_tb.vcd");
        $dumpvars(0, fountain_v1_tb);

        // Initialize inputs
        clk = 0;
        rst = 0;
        start = 0;
        data_in = 8'b00000000;
        #10 rst = 1;
        #10 rst = 0;

        // Start the module
        #10 start = 1;
        #100 start = 0;

        // Send data
        #50 data_in = 8'b01010101;
        #50 data_in = 8'b10101010;

        // Wait for the module to finish
        #100000 $finish;
    end

    always #5 clk = ~clk;

endmodule

parallel/fountain_v1_tb.vcd
$date
	Fri Apr 28 19:40:00 2023
$end
$version
	Icarus Verilog
$end
$timescale
	1ns
$end
$scope module fountain_v1_tb $end
$var wire 64 ! data_out [63:0] $end
$var reg 1 " clk $end
$var reg 64 # data_in [63:0] $end
$var reg 1 $ rst $end
$var reg 1 % start $end
$scope module uut $end
$var wire 1 " clk $end
$var wire 64 & data_in [63:0] $end
$var wire 1 ' reset $end
$var wire 1 % start $end
$var parameter 32 ( K $end
$var parameter 32 ) L $end
$var parameter 32 * N $end
$var reg 8 + data_in_reg [7:0] $end
$var reg 64 , data_out [63:0] $end
$var reg 1 - done $end
$var reg 64 . lfsr [63:0] $end
$var integer 32 / i [31:0] $end
$var integer 32 0 i1 [31:0] $end
$var integer 32 1 j [31:0] $end
$var integer 32 2 j1 [31:0] $end
$var integer 32 3 k [31:0] $end
$var integer 32 4 l [31:0] $end
$var integer 32 5 m [31:0] $end
$upscope $end
$upscope $end
$enddefinitions $end
$comment Show the parameter values. $end
$dumpall
b11111111 *
b1010 )
b100000 (
$end
#0
$dumpvars
bx 5
bx 4
bx 3
bx 2
b100000 1
bx 0
b11111111 /
b0xxxxxxxx .
x-
bx ,
bx +
z'
b0 &
0%
0$
b0 #
0"
bx !
$end
#5
b0xxxxxxxxx .
1"
#10
0"
1$
#15
b0xxxxxxxxxx .
1"
#20
0"
0$
#25
b0xxxxxxxxxxx .
1"
#30
0"
1%
#35
0-
b0xxxxxxxx !
b0xxxxxxxx ,
b0xxxxxxxxxxxx .
b100000 5
b0 4
b100000 2
b0 0
b0 3
b100000 /
1"
#36
0-
b100000 5
b1 4
#37
0-
b100000 5
b10 4
#38
0-
b100000 5
b11 4
#39
0-
b100000 5
b100 4
#40
0-
b100000 5
b101 4
0"
#41
0-
b100000 5
b110 4
#42
0-
b100000 5
b111 4
#43
0-
b100000 5
b100000 2
b1 0
b0 4
#44
0-
b100000 5
b1 4
#45
b0xxxxxxxxxxxxx .
0-
b100000 /
b100000 5
b10 4
1"
#46
0-
b100000 5
b11 4
#47
0-
b100000 5
b100 4
#48
0-
b100000 5
b101 4
#49
0-
b100000 5
b110 4
#50
0-
b100000 5
b111 4
0"
#51
0-
b100000 5
b100000 2
b10 0
b0 4
#52
0-
b100000 5
b1 4
#53
0-
b100000 5
b10 4
#54
0-
b100000 5
b11 4
#55
b0xxxxxxxxxxxxxx .
0-
b100000 /
b100000 5
b100 4
1"
#56
0-
b100000 5
b101 4
#57
0-
b100000 5
b110 4
#58
0-
b100000 5
b111 4
#59
0-
b100000 5
b100000 2
b11 0
b0 4
#60
0-
b100000 5
b1 4
0"
#61
0-
b100000 5
b10 4
#62
0-
b100000 5
b11 4
#63
0-
b100000 5
b100 4
#64
0-
b100000 5
b101 4
#65
b0xxxxxxxxxxxxxxx .
0-
b100000 /
b100000 5
b110 4
1"
#66
0-
b100000 5
b111 4
#67
0-
b100000 5
b100000 2
b100 0
b0 4
#68
0-
b100000 5
b1 4
#69
0-
b100000 5
b10 4
#70
0-
b100000 5
b11 4
0"
#71
0-
b100000 5
b100 4
#72
0-
b100000 5
b101 4
#73
0-
b100000 5
b110 4
#74
0-
b100000 5
b111 4
#75
b0xxxxxxxxxxxxxxxx .
0-
b100000 /
b100000 5
b100000 2
b101 0
b0 4
1"
#76
0-
b100000 5
b1 4
#77
0-
b100000 5
b10 4
#78
0-
b100000 5
b11 4
#79
0-
b100000 5
b100 4
#80
0-
b100000 5
b101 4
0"
#81
0-
b100000 5
b110 4
#82
0-
b100000 5
b111 4
#83
0-
b100000 5
b100000 2
b110 0
b0 4
#84
0-
b100000 5
b1 4
#85
b0xxxxxxxxxxxxxxxxx .
0-
b100000 /
b100000 5
b10 4
1"
#86
0-
b100000 5
b11 4
#87
0-
b100000 5
b100 4
#88
0-
b100000 5
b101 4
#89
0-
b100000 5
b110 4
#90
0-
b100000 5
b111 4
0"
#91
0-
b100000 5
b100000 2
b111 0
b0 4
#92
0-
b100000 5
b1 4
#93
0-
b100000 5
b10 4
#94
0-
b100000 5
b11 4
#95
b0xxxxxxxxxxxxxxxxxx .
0-
b100000 /
b100000 5
b100 4
1"
#96
0-
b100000 5
b101 4
#97
0-
b100000 5
b110 4
#98
0-
b100000 5
b111 4
#99
0-
b100000 5
b100000 2
b1000 0
b0 4
#100
0-
b100000 5
b1 4
0"
#101
0-
b100000 5
b10 4
#102
0-
b100000 5
b11 4
#103
0-
b100000 5
b100 4
#104
0-
b100000 5
b101 4
#105
b0xxxxxxxxxxxxxxxxxxx .
0-
b100000 /
b100000 5
b110 4
1"
#106
0-
b100000 5
b111 4
#107
0-
b100000 5
b100000 2
b1001 0
b0 4
#108
0-
b100000 5
b1 4
#109
0-
b100000 5
b10 4
#110
0-
b100000 5
b11 4
0"
#111
0-
b100000 5
b100 4
#112
0-
b100000 5
b101 4
#113
0-
b100000 5
b110 4
#114
0-
b100000 5
b111 4
#115
b0xxxxxxxxxxxxxxxxxxxx .
0-
b100000 /
b100000 5
b100000 2
b1010 0
b0 4
1"
#116
0-
b100000 5
b1 4
#117
0-
b100000 5
b10 4
#118
0-
b100000 5
b11 4
#119
0-
b100000 5
b100 4
#120
0-
b100000 5
b101 4
0"
#121
0-
b100000 5
b110 4
#122
0-
b100000 5
b111 4
#123
0-
b100000 5
b100000 2
b1011 0
b0 4
#124
0-
b100000 5
b1 4
#125
b0xxxxxxxxxxxxxxxxxxxxx .
0-
b100000 /
b100000 5
b10 4
1"
#126
0-
b100000 5
b11 4
#127
0-
b100000 5
b100 4
#128
0-
b100000 5
b101 4
#129
0-
b100000 5
b110 4
#130
0-
b100000 5
b111 4
0"
0%
#131
0-
b100000 5
b100000 2
b1100 0
b0 4
#132
0-
b100000 5
b1 4
#133
0-
b100000 5
b10 4
#134
0-
b100000 5
b11 4
#135
b0xxxxxxxxxxxxxxxxxxxxxx .
0-
b100000 5
b100 4
1"
#136
0-
b100000 5
b101 4
#137
0-
b100000 5
b110 4
#138
0-
b100000 5
b111 4
#139
0-
b100000 5
b100000 2
b1101 0
b0 4
#140
0-
b100000 5
b1 4
0"
#141
0-
b100000 5
b10 4
#142
0-
b100000 5
b11 4
#143
0-
b100000 5
b100 4
#144
0-
b100000 5
b101 4
#145
b0xxxxxxxxxxxxxxxxxxxxxxx .
0-
b100000 5
b110 4
1"
#146
0-
b100000 5
b111 4
#147
0-
b100000 5
b100000 2
b1110 0
b0 4
#148
0-
b100000 5
b1 4
#149
0-
b100000 5
b10 4
#150
0-
b100000 5
b11 4
0"
#151
0-
b100000 5
b100 4
#152
0-
b100000 5
b101 4
#153
0-
b100000 5
b110 4
#154
0-
b100000 5
b111 4
#155
b0xxxxxxxxxxxxxxxxxxxxxxxx .
0-
b100000 5
b100000 2
b1111 0
b0 4
1"
#156
0-
b100000 5
b1 4
#157
0-
b100000 5
b10 4
#158
0-
b100000 5
b11 4
#159
0-
b100000 5
b100 4
#160
0-
b100000 5
b101 4
0"
#161
0-
b100000 5
b110 4
#162
0-
b100000 5
b111 4
#163
0-
b100000 5
b100000 2
b10000 0
b0 4
#164
0-
b100000 5
b1 4
#165
b0xxxxxxxxxxxxxxxxxxxxxxxxx .
0-
b100000 5
b10 4
1"
#166
0-
b100000 5
b11 4
#167
0-
b100000 5
b100 4
#168
0-
b100000 5
b101 4
#169
0-
b100000 5
b110 4
#170
0-
b100000 5
b111 4
0"
#171
0-
b100000 5
b100000 2
b10001 0
b0 4
#172
0-
b100000 5
b1 4
#173
0-
b100000 5
b10 4
#174
0-
b100000 5
b11 4
#175
b0xxxxxxxxxxxxxxxxxxxxxxxxxx .
0-
b100000 5
b100 4
1"
#176
0-
b100000 5
b101 4
#177
0-
b100000 5
b110 4
#178
0-
b100000 5
b111 4
#179
0-
b100000 5
b100000 2
b10010 0
b0 4
#180
0-
b100000 5
b1 4
0"
b1010101 #
b1010101 &
#181
0-
b100000 5
b10 4
#182
0-
b100000 5
b11 4
#183
0-
b100000 5
b100 4
#184
0-
b100000 5
b101 4
#185
b0xxxxxxxxxxxxxxxxxxxxxxxxxxx .
0-
b100000 5
b110 4
1"
#186
0-
b100000 5
b111 4
#187
0-
b100000 5
b100000 2
b10011 0
b0 4
#188
0-
b100000 5
b1 4
#189
0-
b100000 5
b10 4
#190
0-
b100000 5
b11 4
0"
#191
0-
b100000 5
b100 4
#192
0-
b100000 5
b101 4
#193
0-
b100000 5
b110 4
#194
0-
b100000 5
b111 4
#195
b0xxxxxxxxxxxxxxxxxxxxxxxxxxxx .
0-
b100000 5
b100000 2
b10100 0
b0 4
1"
#196
0-
b100000 5
b1 4
#197
0-
b100000 5
b10 4
#198
0-
b100000 5
b11 4
#199
0-
b100000 5
b100 4
#200
0-
b100000 5
b101 4
0"
#201
0-
b100000 5
b110 4
#202
0-
b100000 5
b111 4
#203
0-
b100000 5
b100000 2
b10101 0
b0 4
#204
0-
b100000 5
b1 4
#205
b0xxxxxxxxxxxxxxxxxxxxxxxxxxxxx .
0-
b100000 5
b10 4
1"
#206
0-
b100000 5
b11 4
#207
0-
b100000 5
b100 4
#208
0-
b100000 5
b101 4
#209
0-
b100000 5
b110 4
#210
0-
b100000 5
b111 4
0"
#211
0-
b100000 5
b100000 2
b10110 0
b0 4
#212
0-
b100000 5
b1 4
#213
0-
b100000 5
b10 4
#214
0-
b100000 5
b11 4
#215
b0xxxxxxxxxxxxxxxxxxxxxxxxxxxxxx .
0-
b100000 5
b100 4
1"
#216
0-
b100000 5
b101 4
#217
0-
b100000 5
b110 4
#218
0-
b100000 5
b111 4
#219
0-
b100000 5
b100000 2
b10111 0
b0 4
#220
0-
b100000 5
b1 4
0"
#221
0-
b100000 5
b10 4
#222
0-
b100000 5
b11 4
#223
0-
b100000 5
b100 4
#224
0-
b100000 5
b101 4
#225
b0xxxxxxxxxxxxxxxxxxxxxxxxxxxxxxx .
0-
b100000 5
b110 4
1"
#226
0-
b100000 5
b111 4
#227
0-
b100000 5
b100000 2
b11000 0
b0 4
#228
0-
b100000 5
b1 4
#229
0-
b100000 5
b10 4
#230
0-
b100000 5
b11 4
0"
b10101010 #
b10101010 &
#231
0-
b100000 5
b100 4
#232
0-
b100000 5
b101 4
#233
0-
b100000 5
b110 4
#234
0-
b100000 5
b111 4
#235
b0xxxxxxxxxxxxxxxxxxxxxxxxxxxxxxxx .
0-
b100000 5
b100000 2
b11001 0
b0 4
1"
#236
0-
b100000 5
b1 4
#237
0-
b100000 5
b10 4
#238
0-
b100000 5
b11 4
#239
0-
b100000 5
b100 4
#240
0-
b100000 5
b101 4
0"
#241
0-
b100000 5
b110 4
#242
0-
b100000 5
b111 4
#243
0-
b100000 5
b100000 2
b11010 0
b0 4
#244
0-
b100000 5
b1 4
#245
b0xxxxxxxxxxxxxxxxxxxxxxxxxxxxxxxxx .
0-
b100000 5
b10 4
1"
#246
0-
b100000 5
b11 4
#247
0-
b100000 5
b100 4
#248
0-
b100000 5
b101 4
#249
0-
b100000 5
b110 4
#250
0-
b100000 5
b111 4
0"
#251
0-
b100000 5
b100000 2
b11011 0
b0 4
#252
0-
b100000 5
b1 4
#253
0-
b100000 5
b10 4
#254
0-
b100000 5
b11 4
#255
b0xxxxxxxxxxxxxxxxxxxxxxxxxxxxxxxxxx .
0-
b100000 5
b100 4
1"
#256
0-
b100000 5
b101 4
#257
0-
b100000 5
b110 4
#258
0-
b100000 5
b111 4
#259
0-
b100000 5
b100000 2
b11100 0
b0 4
#260
0-
b100000 5
b1 4
0"
#261
0-
b100000 5
b10 4
#262
0-
b100000 5
b11 4
#263
0-
b100000 5
b100 4
#264
0-
b100000 5
b101 4
#265
b0xxxxxxxxxxxxxxxxxxxxxxxxxxxxxxxxxxx .
0-
b100000 5
b110 4
1"
#266
0-
b100000 5
b111 4
#267
0-
b100000 5
b100000 2
b11101 0
b0 4
#268
0-
b100000 5
b1 4
#269
0-
b100000 5
b10 4
#270
0-
b100000 5
b11 4
0"
#271
0-
b100000 5
b100 4
#272
0-
b100000 5
b101 4
#273
0-
b100000 5
b110 4
#274
0-
b100000 5
b111 4
#275
b0xxxxxxxxxxxxxxxxxxxxxxxxxxxxxxxxxxxx .
0-
b100000 5
b100000 2
b11110 0
b0 4
1"
#276
0-
b100000 5
b1 4
#277
0-
b100000 5
b10 4
#278
0-
b100000 5
b11 4
#279
0-
b100000 5
b100 4
#280
0-
b100000 5
b101 4
0"
#281
0-
b100000 5
b110 4
#282
0-
b100000 5
b111 4
#283
0-
b100000 5
b100000 2
b11111 0
b0 4
#284
0-
b100000 5
b1 4
#285
b0xxxxxxxxxxxxxxxxxxxxxxxxxxxxxxxxxxxxx .
0-
b100000 5
b10 4
1"
#286
0-
b100000 5
b11 4
#287
0-
b100000 5
b100 4
#288
0-
b100000 5
b101 4
#289
0-
b100000 5
b110 4
#290
0-
b100000 5
b111 4
0"
#291
b0 !
b0 ,
0-
b100000 5
b100000 2
b100000 0
b0 4
#292
0-
b100000 5
b1 4
#293
0-
b100000 5
b10 4
#294
0-
b100000 5
b11 4
#295
b0xxxxxxxxxxxxxxxxxxxxxxxxxxxxxxxxxxxxxx .
0-
b100000 5
b100 4
1"
#296
0-
b100000 5
b101 4
#297
0-
b100000 5
b110 4
#298
0-
b100000 5
b111 4
#299
b0xxxxxxxx !
b0xxxxxxxx ,
0-
b100000 5
b100000 2
b100001 0
b0 4
#300
0-
b100000 5
b1 4
0"
#301
0-
b100000 5
b10 4
#302
0-
b100000 5
b11 4
#303
0-
b100000 5
b100 4
#304
0-
b100000 5
b101 4
#305
b0xxxxxxxxxxxxxxxxxxxxxxxxxxxxxxxxxxxxxxx .
0-
b100000 5
b110 4
1"
#306
0-
b100000 5
b111 4
#307
0-
b100000 5
b100000 2
b100010 0
b0 4
#308
0-
b100000 5
b1 4
#309
0-
b100000 5
b10 4
#310
0-
b100000 5
b11 4
0"
#311
0-
b100000 5
b100 4
#312
0-
b100000 5
b101 4
#313
0-
b100000 5
b110 4
#314
0-
b100000 5
b111 4
#315
b0xxxxxxxxxxxxxxxxxxxxxxxxxxxxxxxxxxxxxxxx .
0-
b100000 5
b100000 2
b100011 0
b0 4
1"
#316
0-
b100000 5
b1 4
#317
0-
b100000 5
b10 4
#318
0-
b100000 5
b11 4
#319
0-
b100000 5
b100 4
#320
0-
b100000 5
b101 4
0"
#321
0-
b100000 5
b110 4
#322
0-
b100000 5
b111 4
#323
0-
b100000 5
b100000 2
b100100 0
b0 4
#324
0-
b100000 5
b1 4
#325
b0xxxxxxxxxxxxxxxxxxxxxxxxxxxxxxxxxxxxxxxxx .
0-
b100000 5
b10 4
1"
#326
0-
b100000 5
b11 4
#327
0-
b100000 5
b100 4
#328
0-
b100000 5
b101 4
#329
0-
b100000 5
b110 4
#330
0-
b100000 5
b111 4
0"
#331
0-
b100000 5
b100000 2
b100101 0
b0 4
#332
0-
b100000 5
b1 4
#333
0-
b100000 5
b10 4
#334
0-
b100000 5
b11 4
#335
b0xxxxxxxxxxxxxxxxxxxxxxxxxxxxxxxxxxxxxxxxxx .
0-
b100000 5
b100 4
1"
#336
0-
b100000 5
b101 4
#337
0-
b100000 5
b110 4
#338
0-
b100000 5
b111 4
#339
0-
b100000 5
b100000 2
b100110 0
b0 4
#340
0-
b100000 5
b1 4
0"
#341
0-
b100000 5
b10 4
#342
0-
b100000 5
b11 4
#343
0-
b100000 5
b100 4
#344
0-
b100000 5
b101 4
#345
b0xxxxxxxxxxxxxxxxxxxxxxxxxxxxxxxxxxxxxxxxxxx .
0-
b100000 5
b110 4
1"
#346
0-
b100000 5
b111 4
#347
0-
b100000 5
b100000 2
b100111 0
b0 4
#348
0-
b100000 5
b1 4
#349
0-
b100000 5
b10 4
#350
0-
b100000 5
b11 4
0"
#351
0-
b100000 5
b100 4
#352
0-
b100000 5
b101 4
#353
0-
b100000 5
b110 4
#354
0-
b100000 5
b111 4
#355
b0xxxxxxxxxxxxxxxxxxxxxxxxxxxxxxxxxxxxxxxxxxxx .
0-
b100000 5
b100000 2
b101000 0
b0 4
1"
#356
0-
b100000 5
b1 4
#357
0-
b100000 5
b10 4
#358
0-
b100000 5
b11 4
#359
0-
b100000 5
b100 4
#360
0-
b100000 5
b101 4
0"
#361
0-
b100000 5
b110 4
#362
0-
b100000 5
b111 4
#363
0-
b100000 5
b100000 2
b101001 0
b0 4
#364
0-
b100000 5
b1 4
#365
b0xxxxxxxxxxxxxxxxxxxxxxxxxxxxxxxxxxxxxxxxxxxxx .
0-
b100000 5
b10 4
1"
#366
0-
b100000 5
b11 4
#367
0-
b100000 5
b100 4
#368
0-
b100000 5
b101 4
#369
0-
b100000 5
b110 4
#370
0-
b100000 5
b111 4
0"
#371
0-
b100000 5
b100000 2
b101010 0
b0 4
#372
0-
b100000 5
b1 4
#373
0-
b100000 5
b10 4
#374
0-
b100000 5
b11 4
#375
b0xxxxxxxxxxxxxxxxxxxxxxxxxxxxxxxxxxxxxxxxxxxxxx .
0-
b100000 5
b100 4
1"
#376
0-
b100000 5
b101 4
#377
0-
b100000 5
b110 4
#378
0-
b100000 5
b111 4
#379
0-
b100000 5
b100000 2
b101011 0
b0 4
#380
0-
b100000 5
b1 4
0"
#381
0-
b100000 5
b10 4
#382
0-
b100000 5
b11 4
#383
0-
b100000 5
b100 4
#384
0-
b100000 5
b101 4
#385
b0xxxxxxxxxxxxxxxxxxxxxxxxxxxxxxxxxxxxxxxxxxxxxxx .
0-
b100000 5
b110 4
1"
#386
0-
b100000 5
b111 4
#387
0-
b100000 5
b100000 2
b101100 0
b0 4
#388
0-
b100000 5
b1 4
#389
0-
b100000 5
b10 4
#390
0-
b100000 5
b11 4
0"
#391
0-
b100000 5
b100 4
#392
0-
b100000 5
b101 4
#393
0-
b100000 5
b110 4
#394
0-
b100000 5
b111 4
#395
b0xxxxxxxxxxxxxxxxxxxxxxxxxxxxxxxxxxxxxxxxxxxxxxxx .
0-
b100000 5
b100000 2
b101101 0
b0 4
1"
#396
0-
b100000 5
b1 4
#397
0-
b100000 5
b10 4
#398
0-
b100000 5
b11 4
#399
0-
b100000 5
b100 4
#400
0-
b100000 5
b101 4
0"
#401
0-
b100000 5
b110 4
#402
0-
b100000 5
b111 4
#403
0-
b100000 5
b100000 2
b101110 0
b0 4
#404
0-
b100000 5
b1 4
#405
b0xxxxxxxxxxxxxxxxxxxxxxxxxxxxxxxxxxxxxxxxxxxxxxxxx .
0-
b100000 5
b10 4
1"
#406
0-
b100000 5
b11 4
#407
0-
b100000 5
b100 4
#408
0-
b100000 5
b101 4
#409
0-
b100000 5
b110 4
#410
0-
b100000 5
b111 4
0"
#411
0-
b100000 5
b100000 2
b101111 0
b0 4
#412
0-
b100000 5
b1 4
#413
0-
b100000 5
b10 4
#414
0-
b100000 5
b11 4
#415
b0xxxxxxxxxxxxxxxxxxxxxxxxxxxxxxxxxxxxxxxxxxxxxxxxxx .
0-
b100000 5
b100 4
1"
#416
0-
b100000 5
b101 4
#417
0-
b100000 5
b110 4
#418
0-
b100000 5
b111 4
#419
0-
b100000 5
b100000 2
b110000 0
b0 4
#420
0-
b100000 5
b1 4
0"
#421
0-
b100000 5
b10 4
#422
0-
b100000 5
b11 4
#423
0-
b100000 5
b100 4
#424
0-
b100000 5
b101 4
#425
b0xxxxxxxxxxxxxxxxxxxxxxxxxxxxxxxxxxxxxxxxxxxxxxxxxxx .
0-
b100000 5
b110 4
1"
#426
0-
b100000 5
b111 4
#427
0-
b100000 5
b100000 2
b110001 0
b0 4
#428
0-
b100000 5
b1 4
#429
0-
b100000 5
b10 4
#430
0-
b100000 5
b11 4
0"
#431
0-
b100000 5
b100 4
#432
0-
b100000 5
b101 4
#433
0-
b100000 5
b110 4
#434
0-
b100000 5
b111 4
#435
b0xxxxxxxxxxxxxxxxxxxxxxxxxxxxxxxxxxxxxxxxxxxxxxxxxxxx .
0-
b100000 5
b100000 2
b110010 0
b0 4
1"
#436
0-
b100000 5
b1 4
#437
0-
b100000 5
b10 4
#438
0-
b100000 5
b11 4
#439
0-
b100000 5
b100 4
#440
0-
b100000 5
b101 4
0"
#441
0-
b100000 5
b110 4
#442
0-
b100000 5
b111 4
#443
0-
b100000 5
b100000 2
b110011 0
b0 4
#444
0-
b100000 5
b1 4
#445
b0xxxxxxxxxxxxxxxxxxxxxxxxxxxxxxxxxxxxxxxxxxxxxxxxxxxxx .
0-
b100000 5
b10 4
1"
#446
0-
b100000 5
b11 4
#447
0-
b100000 5
b100 4
#448
0-
b100000 5
b101 4
#449
0-
b100000 5
b110 4
#450
0-
b100000 5
b111 4
0"
#451
0-
b100000 5
b100000 2
b110100 0
b0 4
#452
0-
b100000 5
b1 4
#453
0-
b100000 5
b10 4
#454
0-
b100000 5
b11 4
#455
b0xxxxxxxxxxxxxxxxxxxxxxxxxxxxxxxxxxxxxxxxxxxxxxxxxxxxxx .
0-
b100000 5
b100 4
1"
#456
0-
b100000 5
b101 4
#457
0-
b100000 5
b110 4
#458
0-
b100000 5
b111 4
#459
0-
b100000 5
b100000 2
b110101 0
b0 4
#460
0-
b100000 5
b1 4
0"
#461
0-
b100000 5
b10 4
#462
0-
b100000 5
b11 4
#463
0-
b100000 5
b100 4
#464
0-
b100000 5
b101 4
#465
b0xxxxxxxxxxxxxxxxxxxxxxxxxxxxxxxxxxxxxxxxxxxxxxxxxxxxxxx .
0-
b100000 5
b110 4
1"
#466
0-
b100000 5
b111 4
#467
0-
b100000 5
b100000 2
b110110 0
b0 4
#468
0-
b100000 5
b1 4
#469
0-
b100000 5
b10 4
#470
0-
b100000 5
b11 4
0"
#471
0-
b100000 5
b100 4
#472
0-
b100000 5
b101 4
#473
0-
b100000 5
b110 4
#474
0-
b100000 5
b111 4
#475
b0xxxxxxxxxxxxxxxxxxxxxxxxxxxxxxxxxxxxxxxxxxxxxxxxxxxxxxxx .
0-
b100000 5
b100000 2
b110111 0
b0 4
1"
#476
0-
b100000 5
b1 4
#477
0-
b100000 5
b10 4
#478
0-
b100000 5
b11 4
#479
0-
b100000 5
b100 4
#480
0-
b100000 5
b101 4
0"
#481
0-
b100000 5
b110 4
#482
0-
b100000 5
b111 4
#483
0-
b100000 5
b100000 2
b111000 0
b0 4
#484
0-
b100000 5
b1 4
#485
b0xxxxxxxxxxxxxxxxxxxxxxxxxxxxxxxxxxxxxxxxxxxxxxxxxxxxxxxxx .
0-
b100000 5
b10 4
1"
#486
0-
b100000 5
b11 4
#487
0-
b100000 5
b100 4
#488
0-
b100000 5
b101 4
#489
0-
b100000 5
b110 4
#490
0-
b100000 5
b111 4
0"
#491
0-
b100000 5
b100000 2
b111001 0
b0 4
#492
0-
b100000 5
b1 4
#493
0-
b100000 5
b10 4
#494
0-
b100000 5
b11 4
#495
b0xxxxxxxxxxxxxxxxxxxxxxxxxxxxxxxxxxxxxxxxxxxxxxxxxxxxxxxxxx .
0-
b100000 5
b100 4
1"
#496
0-
b100000 5
b101 4
#497
0-
b100000 5
b110 4
#498
0-
b100000 5
b111 4
#499
0-
b100000 5
b100000 2
b111010 0
b0 4
#500
0-
b100000 5
b1 4
0"
#501
0-
b100000 5
b10 4
#502
0-
b100000 5
b11 4
#503
0-
b100000 5
b100 4
#504
0-
b100000 5
b101 4
#505
b0xxxxxxxxxxxxxxxxxxxxxxxxxxxxxxxxxxxxxxxxxxxxxxxxxxxxxxxxxxx .
0-
b100000 5
b110 4
1"
#506
0-
b100000 5
b111 4
#507
0-
b100000 5
b100000 2
b111011 0
b0 4
#508
0-
b100000 5
b1 4
#509
0-
b100000 5
b10 4
#510
0-
b100000 5
b11 4
0"
#511
0-
b100000 5
b100 4
#512
0-
b100000 5
b101 4
#513
0-
b100000 5
b110 4
#514
0-
b100000 5
b111 4
#515
b0xxxxxxxxxxxxxxxxxxxxxxxxxxxxxxxxxxxxxxxxxxxxxxxxxxxxxxxxxxxx .
0-
b100000 5
b100000 2
b111100 0
b0 4
1"
#516
0-
b100000 5
b1 4
#517
0-
b100000 5
b10 4
#518
0-
b100000 5
b11 4
#519
0-
b100000 5
b100 4
#520
0-
b100000 5
b101 4
0"
#521
0-
b100000 5
b110 4
#522
0-
b100000 5
b111 4
#523
0-
b100000 5
b100000 2
b111101 0
b0 4
#524
0-
b100000 5
b1 4
#525
b0xxxxxxxxxxxxxxxxxxxxxxxxxxxxxxxxxxxxxxxxxxxxxxxxxxxxxxxxxxxxx .
0-
b100000 5
b10 4
1"
#526
0-
b100000 5
b11 4
#527
0-
b100000 5
b100 4
#528
0-
b100000 5
b101 4
#529
0-
b100000 5
b110 4
#530
0-
b100000 5
b111 4
0"
#531
0-
b100000 5
b100000 2
b111110 0
b0 4
#532
0-
b100000 5
b1 4
#533
0-
b100000 5
b10 4
#534
0-
b100000 5
b11 4
#535
b0xxxxxxxxxxxxxxxxxxxxxxxxxxxxxxxxxxxxxxxxxxxxxxxxxxxxxxxxxxxxxx .
0-
b100000 5
b100 4
1"
#536
0-
b100000 5
b101 4
#537
0-
b100000 5
b110 4
#538
0-
b100000 5
b111 4
#539
0-
b100000 5
b100000 2
b111111 0
b0 4
#540
0-
b100000 5
b1 4
0"
#541
0-
b100000 5
b10 4
#542
0-
b100000 5
b11 4
#543
0-
b100000 5
b100 4
#544
0-
b100000 5
b101 4
#545
b0xxxxxxxxxxxxxxxxxxxxxxxxxxxxxxxxxxxxxxxxxxxxxxxxxxxxxxxxxxxxxxx .
0-
b100000 5
b110 4
1"
#546
0-
b100000 5
b111 4
#547
0-
b100000 5
b100000 2
b1000000 0
b0 4
#548
0-
b100000 5
b1 4
#549
0-
b100000 5
b10 4
#550
0-
b100000 5
b11 4
0"
#551
0-
b100000 5
b100 4
#552
0-
b100000 5
b101 4
#553
0-
b100000 5
b110 4
#554
0-
b100000 5
b111 4
#555
bx .
0-
b100000 5
b100000 2
b1000001 0
b0 4
1"
#556
0-
b100000 5
b1 4
#557
0-
b100000 5
b10 4
#558
0-
b100000 5
b11 4
#559
0-
b100000 5
b100 4
#560
0-
b100000 5
b101 4
0"
#561
0-
b100000 5
b110 4
#562
0-
b100000 5
b111 4
#563
0-
b100000 5
b100000 2
b1000010 0
b0 4
#564
0-
b100000 5
b1 4
#565
0-
b100000 5
b10 4
1"
#566
0-
b100000 5
b11 4
#567
0-
b100000 5
b100 4
#568
0-
b100000 5
b101 4
#569
0-
b100000 5
b110 4
#570
0-
b100000 5
b111 4
0"
#571
0-
b100000 5
b100000 2
b1000011 0
b0 4
#572
0-
b100000 5
b1 4
#573
0-
b100000 5
b10 4
#574
0-
b100000 5
b11 4
#575
0-
b100000 5
b100 4
1"
#576
0-
b100000 5
b101 4
#577
0-
b100000 5
b110 4
#578
0-
b100000 5
b111 4
#579
0-
b100000 5
b100000 2
b1000100 0
b0 4
#580
0-
b100000 5
b1 4
0"
#581
0-
b100000 5
b10 4
#582
0-
b100000 5
b11 4
#583
0-
b100000 5
b100 4
#584
0-
b100000 5
b101 4
#585
0-
b100000 5
b110 4
1"
#586
0-
b100000 5
b111 4
#587
0-
b100000 5
b100000 2
b1000101 0
b0 4
#588
0-
b100000 5
b1 4
#589
0-
b100000 5
b10 4
#590
0-
b100000 5
b11 4
0"
