basic/fountain_v1_basic.v
module fountain_v1_basic(
  input clk,
  input reset,
  input start,
  output reg done,
  input wire [63:0] data_in,
  output reg [63:0] data_out
);

  parameter N = 255; // block size
  parameter L = 10; // number of blocks to encode
  parameter K = 32; // number of non-zero coefficients

  // Linear Feedback Shift Register
  reg [63:0] lfsr;
  always @(posedge clk) begin
    if (reset) begin
      lfsr <= 8'hBC;
    end
    else begin
      lfsr <= {lfsr[62:0], lfsr[25] ^ lfsr[12] ^ lfsr[0]};
    end
  end

  // Generate matrix B
  reg [7:0] b [0:N-1][0:K-1];
  integer i, j;
  initial begin
    for (i = 0; i < N; i = i+1) begin
      for (j = 0; j < K; j = j+1) begin
        b[i][j] = lfsr;
        lfsr = {lfsr[6:0], lfsr[7] ^ lfsr[2]};
      end
    end
  end

  // Generate vector h
  reg [7:0] h [0:K-1];
  reg [7:0] data_in_reg; // new variable to store input data
  always @(posedge clk) begin
    if (start) begin
      for (i = 0; i < K; i = i+1) begin
        h[i] <= data_in_reg; // use data_in_reg instead of data_in
        data_in_reg <= data_in_reg + 1; // manipulate data_in_reg
      end
    end
  end

  // Generate vector z
  reg [7:0] z [0:N-1];
  reg [7:0] s [0:K-1];
  integer k, l, m;
  always @(posedge clk) begin
    if (start) begin
      for (k = 0; k < L; k = k+1) begin
        for (i = 0; i < N; i = i+1) begin
          z[i] = 0;
          for (j = 0; j < K; j = j+1) begin
            s[j] = h[j] ^ b[i][j];
          end
          for (l = 0; l < 8; l = l+1) begin
            for (m = 0; m < K; m = m+1) begin
              if (s[m][l] == 1) begin
                z[i][l] = z[i][l] ^ 1;
              end
            end
          end
          data_out <= z[i];
          done <= 0;
          #1 done <= 1;
        end
      end
    end
  end

endmodule

basic/fountain_v1_tb.v
`timescale 1ns/1ns
`include "fountain_v1_basic.v"

module fountain_v1_tb();

    reg clk;
    reg rst;
    reg start;
    reg [63:0] data_in;
    wire [63:0] data_out;

    fountain_v1_basic uut (
        .clk(clk),
        .start(start),
        .data_in(data_in),
        .data_out(data_out)
    );

    initial begin
        $dumpfile("fountain_v1_tb.vcd");
        $dumpvars(0, fountain_v1_tb);

        // Initialize inputs
        clk = 0;
        rst = 0;
        start = 0;
        data_in = 8'b00000000;
        #10 rst = 1;
        #10 rst = 0;

        // Start the module
        #10 start = 1;
        #100 start = 0;

        // Send data
        #50 data_in = 8'b01010101;
        #50 data_in = 8'b10101010;

        // Wait for the module to finish
        #100000 $finish;
    end

    always #5 clk = ~clk;

endmodule

basic/fountain_v1_tb.vcd
$date
	Fri Apr 28 18:12:37 2023
$end
$version
	Icarus Verilog
$end
$timescale
	1ns
$end
$scope module fountain_v1_tb $end
$var wire 64 ! data_out [63:0] $end
$var reg 1 " clk $end
$var reg 64 # data_in [63:0] $end
$var reg 1 $ rst $end
$var reg 1 % start $end
$scope module uut $end
$var wire 1 " clk $end
$var wire 64 & data_in [63:0] $end
$var wire 1 ' reset $end
$var wire 1 % start $end
$var parameter 32 ( K $end
$var parameter 32 ) L $end
$var parameter 32 * N $end
$var reg 8 + data_in_reg [7:0] $end
$var reg 64 , data_out [63:0] $end
$var reg 1 - done $end
$var reg 64 . lfsr [63:0] $end
$var integer 32 / i [31:0] $end
$var integer 32 0 j [31:0] $end
$var integer 32 1 k [31:0] $end
$var integer 32 2 l [31:0] $end
$var integer 32 3 m [31:0] $end
$upscope $end
$upscope $end
$enddefinitions $end
$comment Show the parameter values. $end
$dumpall
b11111111 *
b1010 )
b100000 (
$end
#0
$dumpvars
bx 3
bx 2
bx 1
b100000 0
b11111111 /
b0xxxxxxxx .
x-
bx ,
bx +
z'
b0 &
0%
0$
b0 #
0"
bx !
$end
#5
b0xxxxxxxxx .
1"
#10
0"
1$
#15
b0xxxxxxxxxx .
1"
#20
0"
0$
#25
b0xxxxxxxxxxx .
1"
#30
0"
1%
#35
0-
b0 !
b0 ,
b0xxxxxxxxxxxx .
b100000 3
b1000 2
b100000 0
b0 1
b0 /
1"
#36
0-
b100000 3
b1000 2
b100000 0
b1 /
#37
0-
b100000 3
b1000 2
b100000 0
b10 /
#38
0-
b100000 3
b1000 2
b100000 0
b11 /
#39
0-
b100000 3
b1000 2
b100000 0
b100 /
#40
0-
b100000 3
b1000 2
b100000 0
b101 /
0"
#41
0-
b100000 3
b1000 2
b100000 0
b110 /
#42
0-
b100000 3
b1000 2
b100000 0
b111 /
#43
0-
b100000 3
b1000 2
b100000 0
b1000 /
#44
0-
b100000 3
b1000 2
b100000 0
b1001 /
#45
b0xxxxxxxxxxxxx .
0-
b100000 3
b1000 2
b100000 0
b100000 /
1"
#46
0-
b100000 3
b1000 2
b100000 0
b100001 /
#47
0-
b100000 3
b1000 2
b100000 0
b100010 /
#48
0-
b100000 3
b1000 2
b100000 0
b100011 /
#49
0-
b100000 3
b1000 2
b100000 0
b100100 /
#50
0-
b100000 3
b1000 2
b100000 0
b100101 /
0"
#51
0-
b100000 3
b1000 2
b100000 0
b100110 /
#52
0-
b100000 3
b1000 2
b100000 0
b100111 /
#53
0-
b100000 3
b1000 2
b100000 0
b101000 /
#54
0-
b100000 3
b1000 2
b100000 0
b101001 /
#55
b0xxxxxxxxxxxxxx .
0-
b100000 3
b1000 2
b100000 0
b100000 /
1"
#56
0-
b100000 3
b1000 2
b100000 0
b100001 /
#57
0-
b100000 3
b1000 2
b100000 0
b100010 /
#58
0-
b100000 3
b1000 2
b100000 0
b100011 /
#59
0-
b100000 3
b1000 2
b100000 0
b100100 /
#60
0-
b100000 3
b1000 2
b100000 0
b100101 /
0"
#61
0-
b100000 3
b1000 2
b100000 0
b100110 /
#62
0-
b100000 3
b1000 2
b100000 0
b100111 /
#63
0-
b100000 3
b1000 2
b100000 0
b101000 /
#64
0-
b100000 3
b1000 2
b100000 0
b101001 /
#65
b0xxxxxxxxxxxxxxx .
0-
b100000 3
b1000 2
b100000 0
b100000 /
1"
#66
0-
b100000 3
b1000 2
b100000 0
b100001 /
#67
0-
b100000 3
b1000 2
b100000 0
b100010 /
#68
0-
b100000 3
b1000 2
b100000 0
b100011 /
#69
0-
b100000 3
b1000 2
b100000 0
b100100 /
#70
0-
b100000 3
b1000 2
b100000 0
b100101 /
0"
#71
0-
b100000 3
b1000 2
b100000 0
b100110 /
#72
0-
b100000 3
b1000 2
b100000 0
b100111 /
#73
0-
b100000 3
b1000 2
b100000 0
b101000 /
#74
0-
b100000 3
b1000 2
b100000 0
b101001 /
#75
b0xxxxxxxxxxxxxxxx .
0-
b100000 3
b1000 2
b100000 0
b100000 /
1"
#76
0-
b100000 3
b1000 2
b100000 0
b100001 /
#77
0-
b100000 3
b1000 2
b100000 0
b100010 /
#78
0-
b100000 3
b1000 2
b100000 0
b100011 /
#79
0-
b100000 3
b1000 2
b100000 0
b100100 /
#80
0-
b100000 3
b1000 2
b100000 0
b100101 /
0"
#81
0-
b100000 3
b1000 2
b100000 0
b100110 /
#82
0-
b100000 3
b1000 2
b100000 0
b100111 /
#83
0-
b100000 3
b1000 2
b100000 0
b101000 /
#84
0-
b100000 3
b1000 2
b100000 0
b101001 /
#85
b0xxxxxxxxxxxxxxxxx .
0-
b100000 3
b1000 2
b100000 0
b100000 /
1"
#86
0-
b100000 3
b1000 2
b100000 0
b100001 /
#87
0-
b100000 3
b1000 2
b100000 0
b100010 /
#88
0-
b100000 3
b1000 2
b100000 0
b100011 /
#89
0-
b100000 3
b1000 2
b100000 0
b100100 /
#90
0-
b100000 3
b1000 2
b100000 0
b100101 /
0"
#91
0-
b100000 3
b1000 2
b100000 0
b100110 /
#92
0-
b100000 3
b1000 2
b100000 0
b100111 /
#93
0-
b100000 3
b1000 2
b100000 0
b101000 /
#94
0-
b100000 3
b1000 2
b100000 0
b101001 /
#95
b0xxxxxxxxxxxxxxxxxx .
0-
b100000 3
b1000 2
b100000 0
b100000 /
1"
#96
0-
b100000 3
b1000 2
b100000 0
b100001 /
#97
0-
b100000 3
b1000 2
b100000 0
b100010 /
#98
0-
b100000 3
b1000 2
b100000 0
b100011 /
#99
0-
b100000 3
b1000 2
b100000 0
b100100 /
#100
0-
b100000 3
b1000 2
b100000 0
b100101 /
0"
#101
0-
b100000 3
b1000 2
b100000 0
b100110 /
#102
0-
b100000 3
b1000 2
b100000 0
b100111 /
#103
0-
b100000 3
b1000 2
b100000 0
b101000 /
#104
0-
b100000 3
b1000 2
b100000 0
b101001 /
#105
b0xxxxxxxxxxxxxxxxxxx .
0-
b100000 3
b1000 2
b100000 0
b100000 /
1"
#106
0-
b100000 3
b1000 2
b100000 0
b100001 /
#107
0-
b100000 3
b1000 2
b100000 0
b100010 /
#108
0-
b100000 3
b1000 2
b100000 0
b100011 /
#109
0-
b100000 3
b1000 2
b100000 0
b100100 /
#110
0-
b100000 3
b1000 2
b100000 0
b100101 /
0"
#111
0-
b100000 3
b1000 2
b100000 0
b100110 /
#112
0-
b100000 3
b1000 2
b100000 0
b100111 /
#113
0-
b100000 3
b1000 2
b100000 0
b101000 /
#114
0-
b100000 3
b1000 2
b100000 0
b101001 /
#115
b0xxxxxxxxxxxxxxxxxxxx .
0-
b100000 3
b1000 2
b100000 0
b100000 /
1"
#116
0-
b100000 3
b1000 2
b100000 0
b100001 /
#117
0-
b100000 3
b1000 2
b100000 0
b100010 /
#118
0-
b100000 3
b1000 2
b100000 0
b100011 /
#119
0-
b100000 3
b1000 2
b100000 0
b100100 /
#120
0-
b100000 3
b1000 2
b100000 0
b100101 /
0"
#121
0-
b100000 3
b1000 2
b100000 0
b100110 /
#122
0-
b100000 3
b1000 2
b100000 0
b100111 /
#123
0-
b100000 3
b1000 2
b100000 0
b101000 /
#124
0-
b100000 3
b1000 2
b100000 0
b101001 /
#125
b0xxxxxxxxxxxxxxxxxxxxx .
0-
b100000 3
b1000 2
b100000 0
b100000 /
1"
#126
0-
b100000 3
b1000 2
b100000 0
b100001 /
#127
0-
b100000 3
b1000 2
b100000 0
b100010 /
#128
0-
b100000 3
b1000 2
b100000 0
b100011 /
#129
0-
b100000 3
b1000 2
b100000 0
b100100 /
#130
0-
b100000 3
b1000 2
b100000 0
b100101 /
0"
0%
#131
0-
b100000 3
b1000 2
b100000 0
b100110 /
#132
0-
b100000 3
b1000 2
b100000 0
b100111 /
#133
0-
b100000 3
b1000 2
b100000 0
b101000 /
#134
0-
b100000 3
b1000 2
b100000 0
b101001 /
#135
b0xxxxxxxxxxxxxxxxxxxxxx .
0-
b100000 3
b1000 2
b100000 0
b101010 /
1"
#136
0-
b100000 3
b1000 2
b100000 0
b101011 /
#137
0-
b100000 3
b1000 2
b100000 0
b101100 /
#138
0-
b100000 3
b1000 2
b100000 0
b101101 /
#139
0-
b100000 3
b1000 2
b100000 0
b101110 /
#140
0-
b100000 3
b1000 2
b100000 0
b101111 /
0"
#141
0-
b100000 3
b1000 2
b100000 0
b110000 /
#142
0-
b100000 3
b1000 2
b100000 0
b110001 /
#143
0-
b100000 3
b1000 2
b100000 0
b110010 /
#144
0-
b100000 3
b1000 2
b100000 0
b110011 /
#145
b0xxxxxxxxxxxxxxxxxxxxxxx .
0-
b100000 3
b1000 2
b100000 0
b110100 /
1"
#146
0-
b100000 3
b1000 2
b100000 0
b110101 /
#147
0-
b100000 3
b1000 2
b100000 0
b110110 /
#148
0-
b100000 3
b1000 2
b100000 0
b110111 /
#149
0-
b100000 3
b1000 2
b100000 0
b111000 /
#150
0-
b100000 3
b1000 2
b100000 0
b111001 /
0"
#151
0-
b100000 3
b1000 2
b100000 0
b111010 /
#152
0-
b100000 3
b1000 2
b100000 0
b111011 /
#153
0-
b100000 3
b1000 2
b100000 0
b111100 /
#154
0-
b100000 3
b1000 2
b100000 0
b111101 /
#155
b0xxxxxxxxxxxxxxxxxxxxxxxx .
0-
b100000 3
b1000 2
b100000 0
b111110 /
1"
#156
0-
b100000 3
b1000 2
b100000 0
b111111 /
#157
0-
b100000 3
b1000 2
b100000 0
b1000000 /
#158
0-
b100000 3
b1000 2
b100000 0
b1000001 /
#159
0-
b100000 3
b1000 2
b100000 0
b1000010 /
#160
0-
b100000 3
b1000 2
b100000 0
b1000011 /
0"
#161
0-
b100000 3
b1000 2
b100000 0
b1000100 /
#162
0-
b100000 3
b1000 2
b100000 0
b1000101 /
#163
0-
b100000 3
b1000 2
b100000 0
b1000110 /
#164
0-
b100000 3
b1000 2
b100000 0
b1000111 /
#165
b0xxxxxxxxxxxxxxxxxxxxxxxxx .
0-
b100000 3
b1000 2
b100000 0
b1001000 /
1"
#166
0-
b100000 3
b1000 2
b100000 0
b1001001 /
#167
0-
b100000 3
b1000 2
b100000 0
b1001010 /
#168
0-
b100000 3
b1000 2
b100000 0
b1001011 /
#169
0-
b100000 3
b1000 2
b100000 0
b1001100 /
#170
0-
b100000 3
b1000 2
b100000 0
b1001101 /
0"
#171
0-
b100000 3
b1000 2
b100000 0
b1001110 /
#172
0-
b100000 3
b1000 2
b100000 0
b1001111 /
#173
0-
b100000 3
b1000 2
b100000 0
b1010000 /
#174
0-
b100000 3
b1000 2
b100000 0
b1010001 /
#175
b0xxxxxxxxxxxxxxxxxxxxxxxxxx .
0-
b100000 3
b1000 2
b100000 0
b1010010 /
1"
#176
0-
b100000 3
b1000 2
b100000 0
b1010011 /
#177
0-
b100000 3
b1000 2
b100000 0
b1010100 /
#178
0-
b100000 3
b1000 2
b100000 0
b1010101 /
#179
0-
b100000 3
b1000 2
b100000 0
b1010110 /
#180
0-
b100000 3
b1000 2
b100000 0
b1010111 /
0"
b1010101 #
b1010101 &
#181
0-
b100000 3
b1000 2
b100000 0
b1011000 /
#182
0-
b100000 3
b1000 2
b100000 0
b1011001 /
#183
0-
b100000 3
b1000 2
b100000 0
b1011010 /
#184
0-
b100000 3
b1000 2
b100000 0
b1011011 /
#185
b0xxxxxxxxxxxxxxxxxxxxxxxxxxx .
0-
b100000 3
b1000 2
b100000 0
b1011100 /
1"
#186
0-
b100000 3
b1000 2
b100000 0
b1011101 /
#187
0-
b100000 3
b1000 2
b100000 0
b1011110 /
#188
0-
b100000 3
b1000 2
b100000 0
b1011111 /
#189
0-
b100000 3
b1000 2
b100000 0
b1100000 /
#190
0-
b100000 3
b1000 2
b100000 0
b1100001 /
0"
#191
0-
b100000 3
b1000 2
b100000 0
b1100010 /
#192
0-
b100000 3
b1000 2
b100000 0
b1100011 /
#193
0-
b100000 3
b1000 2
b100000 0
b1100100 /
#194
0-
b100000 3
b1000 2
b100000 0
b1100101 /
#195
b0xxxxxxxxxxxxxxxxxxxxxxxxxxxx .
0-
b100000 3
b1000 2
b100000 0
b1100110 /
1"
#196
0-
b100000 3
b1000 2
b100000 0
b1100111 /
#197
0-
b100000 3
b1000 2
b100000 0
b1101000 /
#198
0-
b100000 3
b1000 2
b100000 0
b1101001 /
#199
0-
b100000 3
b1000 2
b100000 0
b1101010 /
#200
0-
b100000 3
b1000 2
b100000 0
b1101011 /
0"
#201
0-
b100000 3
b1000 2
b100000 0
b1101100 /
#202
0-
b100000 3
b1000 2
b100000 0
b1101101 /
#203
0-
b100000 3
b1000 2
b100000 0
b1101110 /
#204
0-
b100000 3
b1000 2
b100000 0
b1101111 /
#205
b0xxxxxxxxxxxxxxxxxxxxxxxxxxxxx .
0-
b100000 3
b1000 2
b100000 0
b1110000 /
1"
#206
0-
b100000 3
b1000 2
b100000 0
b1110001 /
#207
0-
b100000 3
b1000 2
b100000 0
b1110010 /
#208
0-
b100000 3
b1000 2
b100000 0
b1110011 /
#209
0-
b100000 3
b1000 2
b100000 0
b1110100 /
#210
0-
b100000 3
b1000 2
b100000 0
b1110101 /
0"
#211
0-
b100000 3
b1000 2
b100000 0
b1110110 /
#212
0-
b100000 3
b1000 2
b100000 0
b1110111 /
#213
0-
b100000 3
b1000 2
b100000 0
b1111000 /
#214
0-
b100000 3
b1000 2
b100000 0
b1111001 /
#215
b0xxxxxxxxxxxxxxxxxxxxxxxxxxxxxx .
0-
b100000 3
b1000 2
b100000 0
b1111010 /
1"
#216
0-
b100000 3
b1000 2
b100000 0
b1111011 /
#217
0-
b100000 3
b1000 2
b100000 0
b1111100 /
#218
0-
b100000 3
b1000 2
b100000 0
b1111101 /
#219
0-
b100000 3
b1000 2
b100000 0
b1111110 /
#220
0-
b100000 3
b1000 2
b100000 0
b1111111 /
0"
#221
0-
b100000 3
b1000 2
b100000 0
b10000000 /
#222
0-
b100000 3
b1000 2
b100000 0
b10000001 /
#223
0-
b100000 3
b1000 2
b100000 0
b10000010 /
#224
0-
b100000 3
b1000 2
b100000 0
b10000011 /
#225
b0xxxxxxxxxxxxxxxxxxxxxxxxxxxxxxx .
0-
b100000 3
b1000 2
b100000 0
b10000100 /
1"
#226
0-
b100000 3
b1000 2
b100000 0
b10000101 /
#227
0-
b100000 3
b1000 2
b100000 0
b10000110 /
#228
0-
b100000 3
b1000 2
b100000 0
b10000111 /
#229
0-
b100000 3
b1000 2
b100000 0
b10001000 /
#230
0-
b100000 3
b1000 2
b100000 0
b10001001 /
0"
b10101010 #
b10101010 &
#231
0-
b100000 3
b1000 2
b100000 0
b10001010 /
#232
0-
b100000 3
b1000 2
b100000 0
b10001011 /
#233
0-
b100000 3
b1000 2
b100000 0
b10001100 /
#234
0-
b100000 3
b1000 2
b100000 0
b10001101 /
#235
b0xxxxxxxxxxxxxxxxxxxxxxxxxxxxxxxx .
0-
b100000 3
b1000 2
b100000 0
b10001110 /
1"
#236
0-
b100000 3
b1000 2
b100000 0
b10001111 /
#237
0-
b100000 3
b1000 2
b100000 0
b10010000 /
#238
0-
b100000 3
b1000 2
b100000 0
b10010001 /
#239
0-
b100000 3
b1000 2
b100000 0
b10010010 /
#240
0-
b100000 3
b1000 2
b100000 0
b10010011 /
0"
#241
0-
b100000 3
b1000 2
b100000 0
b10010100 /
#242
0-
b100000 3
b1000 2
b100000 0
b10010101 /
#243
0-
b100000 3
b1000 2
b100000 0
b10010110 /
#244
0-
b100000 3
b1000 2
b100000 0
b10010111 /
#245
b0xxxxxxxxxxxxxxxxxxxxxxxxxxxxxxxxx .
0-
b100000 3
b1000 2
b100000 0
b10011000 /
1"
#246
0-
b100000 3
b1000 2
b100000 0
b10011001 /
#247
0-
b100000 3
b1000 2
b100000 0
b10011010 /
#248
0-
b100000 3
b1000 2
b100000 0
b10011011 /
#249
0-
b100000 3
b1000 2
b100000 0
b10011100 /
#250
0-
b100000 3
b1000 2
b100000 0
b10011101 /
0"
#251
0-
b100000 3
b1000 2
b100000 0
b10011110 /
#252
0-
b100000 3
b1000 2
b100000 0
b10011111 /
#253
0-
b100000 3
b1000 2
b100000 0
b10100000 /
#254
0-
b100000 3
b1000 2
b100000 0
b10100001 /
#255
b0xxxxxxxxxxxxxxxxxxxxxxxxxxxxxxxxxx .
0-
b100000 3
b1000 2
b100000 0
b10100010 /
1"
#256
0-
b100000 3
b1000 2
b100000 0
b10100011 /
#257
0-
b100000 3
b1000 2
b100000 0
b10100100 /
#258
0-
b100000 3
b1000 2
b100000 0
b10100101 /
#259
0-
b100000 3
b1000 2
b100000 0
b10100110 /
#260
0-
b100000 3
b1000 2
b100000 0
b10100111 /
0"
#261
0-
b100000 3
b1000 2
b100000 0
b10101000 /
#262
0-
b100000 3
b1000 2
b100000 0
b10101001 /
#263
0-
b100000 3
b1000 2
b100000 0
b10101010 /
#264
0-
b100000 3
b1000 2
b100000 0
b10101011 /
#265
b0xxxxxxxxxxxxxxxxxxxxxxxxxxxxxxxxxxx .
0-
b100000 3
b1000 2
b100000 0
b10101100 /
1"
#266
0-
b100000 3
b1000 2
b100000 0
b10101101 /
#267
0-
b100000 3
b1000 2
b100000 0
b10101110 /
#268
0-
b100000 3
b1000 2
b100000 0
b10101111 /
#269
0-
b100000 3
b1000 2
b100000 0
b10110000 /
#270
0-
b100000 3
b1000 2
b100000 0
b10110001 /
0"
#271
0-
b100000 3
b1000 2
b100000 0
b10110010 /
#272
0-
b100000 3
b1000 2
b100000 0
b10110011 /
#273
0-
b100000 3
b1000 2
b100000 0
b10110100 /
#274
0-
b100000 3
b1000 2
b100000 0
b10110101 /
#275
b0xxxxxxxxxxxxxxxxxxxxxxxxxxxxxxxxxxxx .
0-
b100000 3
b1000 2
b100000 0
b10110110 /
1"
#276
0-
b100000 3
b1000 2
b100000 0
b10110111 /
#277
0-
b100000 3
b1000 2
b100000 0
b10111000 /
#278
0-
b100000 3
b1000 2
b100000 0
b10111001 /
#279
0-
b100000 3
b1000 2
b100000 0
b10111010 /
#280
0-
b100000 3
b1000 2
b100000 0
b10111011 /
0"
#281
0-
b100000 3
b1000 2
b100000 0
b10111100 /
#282
0-
b100000 3
b1000 2
b100000 0
b10111101 /
#283
0-
b100000 3
b1000 2
b100000 0
b10111110 /
#284
0-
b100000 3
b1000 2
b100000 0
b10111111 /
#285
b0xxxxxxxxxxxxxxxxxxxxxxxxxxxxxxxxxxxxx .
0-
b100000 3
b1000 2
b100000 0
b11000000 /
1"
#286
0-
b100000 3
b1000 2
b100000 0
b11000001 /
#287
0-
b100000 3
b1000 2
b100000 0
b11000010 /
#288
0-
b100000 3
b1000 2
b100000 0
b11000011 /
#289
0-
b100000 3
b1000 2
b100000 0
b11000100 /
#290
0-
b100000 3
b1000 2
b100000 0
b11000101 /
0"
#291
0-
b100000 3
b1000 2
b100000 0
b11000110 /
#292
0-
b100000 3
b1000 2
b100000 0
b11000111 /
#293
0-
b100000 3
b1000 2
b100000 0
b11001000 /
#294
0-
b100000 3
b1000 2
b100000 0
b11001001 /
#295
b0xxxxxxxxxxxxxxxxxxxxxxxxxxxxxxxxxxxxxx .
0-
b100000 3
b1000 2
b100000 0
b11001010 /
1"
#296
0-
b100000 3
b1000 2
b100000 0
b11001011 /
#297
0-
b100000 3
b1000 2
b100000 0
b11001100 /
#298
0-
b100000 3
b1000 2
b100000 0
b11001101 /
#299
0-
b100000 3
b1000 2
b100000 0
b11001110 /
#300
0-
b100000 3
b1000 2
b100000 0
b11001111 /
0"
#301
0-
b100000 3
b1000 2
b100000 0
b11010000 /
#302
0-
b100000 3
b1000 2
b100000 0
b11010001 /
#303
0-
b100000 3
b1000 2
b100000 0
b11010010 /
#304
0-
b100000 3
b1000 2
b100000 0
b11010011 /
#305
b0xxxxxxxxxxxxxxxxxxxxxxxxxxxxxxxxxxxxxxx .
0-
b100000 3
b1000 2
b100000 0
b11010100 /
1"
#306
0-
b100000 3
b1000 2
b100000 0
b11010101 /
#307
0-
b100000 3
b1000 2
b100000 0
b11010110 /
#308
0-
b100000 3
b1000 2
b100000 0
b11010111 /
#309
0-
b100000 3
b1000 2
b100000 0
b11011000 /
#310
0-
b100000 3
b1000 2
b100000 0
b11011001 /
0"
#311
0-
b100000 3
b1000 2
b100000 0
b11011010 /
#312
0-
b100000 3
b1000 2
b100000 0
b11011011 /
#313
0-
b100000 3
b1000 2
b100000 0
b11011100 /
#314
0-
b100000 3
b1000 2
b100000 0
b11011101 /
#315
b0xxxxxxxxxxxxxxxxxxxxxxxxxxxxxxxxxxxxxxxx .
0-
b100000 3
b1000 2
b100000 0
b11011110 /
1"
#316
0-
b100000 3
b1000 2
b100000 0
b11011111 /
#317
0-
b100000 3
b1000 2
b100000 0
b11100000 /
#318
0-
b100000 3
b1000 2
b100000 0
b11100001 /
#319
0-
b100000 3
b1000 2
b100000 0
b11100010 /
#320
0-
b100000 3
b1000 2
b100000 0
b11100011 /
0"
#321
0-
b100000 3
b1000 2
b100000 0
b11100100 /
#322
0-
b100000 3
b1000 2
b100000 0
b11100101 /
#323
0-
b100000 3
b1000 2
b100000 0
b11100110 /
#324
0-
b100000 3
b1000 2
b100000 0
b11100111 /
#325
b0xxxxxxxxxxxxxxxxxxxxxxxxxxxxxxxxxxxxxxxxx .
0-
b100000 3
b1000 2
b100000 0
b11101000 /
1"
#326
0-
b100000 3
b1000 2
b100000 0
b11101001 /
#327
0-
b100000 3
b1000 2
b100000 0
b11101010 /
#328
0-
b100000 3
b1000 2
b100000 0
b11101011 /
#329
0-
b100000 3
b1000 2
b100000 0
b11101100 /
#330
0-
b100000 3
b1000 2
b100000 0
b11101101 /
0"
#331
0-
b100000 3
b1000 2
b100000 0
b11101110 /
#332
0-
b100000 3
b1000 2
b100000 0
b11101111 /
#333
0-
b100000 3
b1000 2
b100000 0
b11110000 /
#334
0-
b100000 3
b1000 2
b100000 0
b11110001 /
#335
b0xxxxxxxxxxxxxxxxxxxxxxxxxxxxxxxxxxxxxxxxxx .
0-
b100000 3
b1000 2
b100000 0
b11110010 /
1"
#336
0-
b100000 3
b1000 2
b100000 0
b11110011 /
#337
0-
b100000 3
b1000 2
b100000 0
b11110100 /
#338
0-
b100000 3
b1000 2
b100000 0
b11110101 /
#339
0-
b100000 3
b1000 2
b100000 0
b11110110 /
#340
0-
b100000 3
b1000 2
b100000 0
b11110111 /
0"
#341
0-
b100000 3
b1000 2
b100000 0
b11111000 /
#342
0-
b100000 3
b1000 2
b100000 0
b11111001 /
#343
0-
b100000 3
b1000 2
b100000 0
b11111010 /
#344
0-
b100000 3
b1000 2
b100000 0
b11111011 /
#345
b0xxxxxxxxxxxxxxxxxxxxxxxxxxxxxxxxxxxxxxxxxxx .
0-
b100000 3
b1000 2
b100000 0
b11111100 /
1"
#346
0-
b100000 3
b1000 2
b100000 0
b11111101 /
#347
0-
b100000 3
b1000 2
b100000 0
b11111110 /
#348
0-
b100000 3
b1000 2
b100000 0
b1 1
b0 /
#349
0-
b100000 3
b1000 2
b100000 0
b1 /
#350
0-
b100000 3
b1000 2
b100000 0
b10 /
0"
#351
0-
b100000 3
b1000 2
b100000 0
b11 /
#352
0-
b100000 3
b1000 2
b100000 0
b100 /
#353
0-
b100000 3
b1000 2
b100000 0
b101 /
#354
0-
b100000 3
b1000 2
b100000 0
b110 /
#355
b0xxxxxxxxxxxxxxxxxxxxxxxxxxxxxxxxxxxxxxxxxxxx .
0-
b100000 3
b1000 2
b100000 0
b111 /
1"
#356
0-
b100000 3
b1000 2
b100000 0
b1000 /
#357
0-
b100000 3
b1000 2
b100000 0
b1001 /
#358
0-
b100000 3
b1000 2
b100000 0
b1010 /
#359
0-
b100000 3
b1000 2
b100000 0
b1011 /
#360
0-
b100000 3
b1000 2
b100000 0
b1100 /
0"
#361
0-
b100000 3
b1000 2
b100000 0
b1101 /
#362
0-
b100000 3
b1000 2
b100000 0
b1110 /
#363
0-
b100000 3
b1000 2
b100000 0
b1111 /
#364
0-
b100000 3
b1000 2
b100000 0
b10000 /
#365
b0xxxxxxxxxxxxxxxxxxxxxxxxxxxxxxxxxxxxxxxxxxxxx .
0-
b100000 3
b1000 2
b100000 0
b10001 /
1"
#366
0-
b100000 3
b1000 2
b100000 0
b10010 /
#367
0-
b100000 3
b1000 2
b100000 0
b10011 /
#368
0-
b100000 3
b1000 2
b100000 0
b10100 /
#369
0-
b100000 3
b1000 2
b100000 0
b10101 /
#370
0-
b100000 3
b1000 2
b100000 0
b10110 /
0"
#371
0-
b100000 3
b1000 2
b100000 0
b10111 /
#372
0-
b100000 3
b1000 2
b100000 0
b11000 /
#373
0-
b100000 3
b1000 2
b100000 0
b11001 /
#374
0-
b100000 3
b1000 2
b100000 0
b11010 /
#375
b0xxxxxxxxxxxxxxxxxxxxxxxxxxxxxxxxxxxxxxxxxxxxxx .
0-
b100000 3
b1000 2
b100000 0
b11011 /
1"
#376
0-
b100000 3
b1000 2
b100000 0
b11100 /
#377
0-
b100000 3
b1000 2
b100000 0
b11101 /
#378
0-
b100000 3
b1000 2
b100000 0
b11110 /
#379
0-
b100000 3
b1000 2
b100000 0
b11111 /
#380
0-
b100000 3
b1000 2
b100000 0
b100000 /
0"
#381
0-
b100000 3
b1000 2
b100000 0
b100001 /
#382
0-
b100000 3
b1000 2
b100000 0
b100010 /
#383
0-
b100000 3
b1000 2
b100000 0
b100011 /
#384
0-
b100000 3
b1000 2
b100000 0
b100100 /
#385
b0xxxxxxxxxxxxxxxxxxxxxxxxxxxxxxxxxxxxxxxxxxxxxxx .
0-
b100000 3
b1000 2
b100000 0
b100101 /
1"
#386
0-
b100000 3
b1000 2
b100000 0
b100110 /
#387
0-
b100000 3
b1000 2
b100000 0
b100111 /
#388
0-
b100000 3
b1000 2
b100000 0
b101000 /
#389
0-
b100000 3
b1000 2
b100000 0
b101001 /
#390
0-
b100000 3
b1000 2
b100000 0
b101010 /
0"
#391
0-
b100000 3
b1000 2
b100000 0
b101011 /
#392
0-
b100000 3
b1000 2
b100000 0
b101100 /
#393
0-
b100000 3
b1000 2
b100000 0
b101101 /
#394
0-
b100000 3
b1000 2
b100000 0
b101110 /
#395
b0xxxxxxxxxxxxxxxxxxxxxxxxxxxxxxxxxxxxxxxxxxxxxxxx .
0-
b100000 3
b1000 2
b100000 0
b101111 /
1"
#396
0-
b100000 3
b1000 2
b100000 0
b110000 /
#397
0-
b100000 3
b1000 2
b100000 0
b110001 /
#398
0-
b100000 3
b1000 2
b100000 0
b110010 /
#399
0-
b100000 3
b1000 2
b100000 0
b110011 /
#400
0-
b100000 3
b1000 2
b100000 0
b110100 /
0"
#401
0-
b100000 3
b1000 2
b100000 0
b110101 /
#402
0-
b100000 3
b1000 2
b100000 0
b110110 /
#403
0-
b100000 3
b1000 2
b100000 0
b110111 /
#404
0-
b100000 3
b1000 2
b100000 0
b111000 /
#405
b0xxxxxxxxxxxxxxxxxxxxxxxxxxxxxxxxxxxxxxxxxxxxxxxxx .
0-
b100000 3
b1000 2
b100000 0
b111001 /
1"
#406
0-
b100000 3
b1000 2
b100000 0
b111010 /
#407
0-
b100000 3
b1000 2
b100000 0
b111011 /
#408
0-
b100000 3
b1000 2
b100000 0
b111100 /
#409
0-
b100000 3
b1000 2
b100000 0
b111101 /
#410
0-
b100000 3
b1000 2
b100000 0
b111110 /
0"
